<?xml version="1.0"?>
<ArrayOfColorSchemaOfColor xmlns:xsi="http://www.w3.org/2001/XMLSchema-instance" xmlns:xsd="http://www.w3.org/2001/XMLSchema">
  <ColorSchemaOfColor>
    <Name>SOA</Name>
    <SelectorPattern>^\[\d{1,2}\.\d{1,2}\.\d{4} \d{2}:\d{2}:\d{2}.\d{3}\]</SelectorPattern>
    <Filters>
      <ColorFilterOfColor>
        <Pattern>\[Warning\]</Pattern>
        <ForegroundColor>DarkYellow</ForegroundColor>
        <BackgroundColor>Black</BackgroundColor>
      </ColorFilterOfColor>
      <ColorFilterOfColor>
        <Pattern>\[Error\]</Pattern>
        <ForegroundColor>#FFFFFF</ForegroundColor>
        <BackgroundColor>#FF0000</BackgroundColor>
      </ColorFilterOfColor>
      <ColorFilterOfColor>
        <Pattern>\[Debug\]</Pattern>
        <ForegroundColor>Gray</ForegroundColor>
        <BackgroundColor>Black</BackgroundColor>
      </ColorFilterOfColor>
      <ColorFilterOfColor>
        <Pattern>\[Info\]</Pattern>
        <ForegroundColor>Cyan</ForegroundColor>
        <BackgroundColor>Black</BackgroundColor>
      </ColorFilterOfColor>
    </Filters>
  </ColorSchemaOfColor>
  <ColorSchemaOfColor>
    <Name>Core</Name>
    <SelectorPattern>^\d{1,2}\.\d{1,2}\.\d{4} \d{2}:\d{2}:\d{2}.\d{3}\|TRID</SelectorPattern>
    <Filters>
      <ColorFilterOfColor>
        <Pattern>\|WARNING\&gt;</Pattern>
        <ForegroundColor>DarkYellow</ForegroundColor>
        <BackgroundColor>Black</BackgroundColor>
      </ColorFilterOfColor>
      <ColorFilterOfColor>
        <Pattern>\|ERROR\&gt;</Pattern>
        <ForegroundColor>White</ForegroundColor>
        <BackgroundColor>Red</BackgroundColor>
      </ColorFilterOfColor>
      <ColorFilterOfColor>
        <Pattern>\|DEBUG\&gt;</Pattern>
        <ForegroundColor>Black</ForegroundColor>
        <BackgroundColor>Gray</BackgroundColor>
      </ColorFilterOfColor>
      <ColorFilterOfColor>
        <Pattern>\|INFO\&gt;</Pattern>
        <ForegroundColor>Cyan</ForegroundColor>
        <BackgroundColor>Black</BackgroundColor>
      </ColorFilterOfColor>
    </Filters>
  </ColorSchemaOfColor>
  <ColorSchemaOfColor>
    <Name>IIS</Name>
    <SelectorPattern>^(\d{4}-\d{2}-\d{2} \d{2}:\d{2}:\d{2}\s)|(#\w+:)</SelectorPattern>
    <Filters>
      <ColorFilterOfColor>
        <Pattern>POST .*- [4-5]\d\d </Pattern>
        <ForegroundColor>White</ForegroundColor>
        <BackgroundColor>Red</BackgroundColor>
      </ColorFilterOfColor>
      <ColorFilterOfColor>
        <Pattern>POST .*- 3\d\d </Pattern>
        <ForegroundColor>DarkYellow</ForegroundColor>
        <BackgroundColor>Black</BackgroundColor>
      </ColorFilterOfColor>
    </Filters>
  </ColorSchemaOfColor>
</ArrayOfColorSchemaOfColor>